ralifore/__init__.py
ralifore-0.0.2.dist-info/METADATA
ralifore-0.0.2.dist-info/WHEEL
ralifore-0.0.2.dist-info/top_level.txt
ralifore-0.0.2.dist-info/RECORD
