Metadata-Version: 2.1
Name: ralifore
Version: 0.0.2
Summary: Raff Libraries for Effective Data Visualization
Home-page: UNKNOWN
Author: Rafka Imanda Putra
Author-email: rafka.0312@gmail.com
License: UNKNOWN
Keywords: python,data visualization
Platform: UNKNOWN
Classifier: Development Status :: 3 - Alpha
Classifier: Intended Audience :: Education
Classifier: Programming Language :: Python :: 2
Classifier: Programming Language :: Python :: 3
Classifier: Operating System :: MacOS :: MacOS X
Classifier: Operating System :: Microsoft :: Windows
Requires-Dist: matplotlib
Requires-Dist: seaborn
